nexus_sample/__init__.py
nexus_sample/main.py
nexus_sample-0.1.0.dist-info/METADATA
nexus_sample-0.1.0.dist-info/WHEEL
nexus_sample-0.1.0.dist-info/RECORD
