Metadata-Version: 2.4
Name: nexus_sample
Version: 0.1.0
Summary: nexus sample
Project-URL: Homepage, https://github.com/
Author-email: thomas <thomas.in@osckorea.com>
Classifier: License :: OSI Approved :: MIT License
Classifier: Operating System :: OS Independent
Classifier: Programming Language :: Python :: 3
Requires-Python: >=3.7
